hin_feature
