Metadata-Version: 1.1
Name: hindi-word-features
Version: 0.2
Summary: A library to calculate Hindi word features instantly
Home-page: https://github.com/shansh8/hindi_word_features
Author: Sajjad Ansari
Author-email: shansh8@gmail.com
License: MIT
Keywords: Hindi word features
Platform: UNKNOWN
Classifier: Development Status :: 4 - Beta
Classifier: Intended Audience :: Developers
Classifier: Topic :: Internet
Classifier: License :: OSI Approved :: MIT License
Classifier: Programming Language :: Python
Classifier: Programming Language :: Python :: 3
Classifier: Programming Language :: Python :: 3.3
Classifier: Programming Language :: Python :: 3.4
Classifier: Programming Language :: Python :: 3.5
